Serializer/__init__.py
Serializer/factory.py
Serializer/Base/__init__.py
Serializer/Base/constants.py
Serializer/Base/deserialization.py
Serializer/Base/serialization.py
Serializer/Json_Serialization/Json_serializer.py
Serializer/Json_Serialization/__init__.py
Serializer/Json_Serialization/logic.py
Serializer/Xml_Serialization/__init__.py
Serializer/Xml_Serialization/logic.py
Serializer/Xml_Serialization/xml_serializer.py
igi_lab3_Oleg-1.0.dist-info/METADATA
igi_lab3_Oleg-1.0.dist-info/WHEEL
igi_lab3_Oleg-1.0.dist-info/top_level.txt
igi_lab3_Oleg-1.0.dist-info/RECORD
