Metadata-Version: 2.1
Name: igi_lab3_Oleg
Version: 1.0
Summary: library for python serialization
Home-page: https://github.com/OlegErshov/IGI/tree/Lab3/Lab3
Author: Ershov Oleg
Author-email: olezhka1629@gmail.com
License: UNKNOWN
Platform: UNKNOWN
Classifier: Intended Audience :: Developers
Classifier: Programming Language :: Python :: 3.10
Classifier: Operating System :: OS Independent
